{"readme.md":"4d8d088c","summary.md":"9912e3e6","_coverpage.md":"c6ff1637","_media_example.md":"28aede6c","awesome.md":"9a0e1e93","cdn.md":"f66f450c","configuration.md":"f7d64dc6","cover.md":"217e636a","custom-navbar.md":"ac75bdf5","deploy.md":"a730ab1b","embed-files.md":"d6440aac","helpers.md":"ab9db3c0","index.md":"32141ae0","language-highlight.md":"6b444cd7","markdown.md":"5bd6490c","more-pages.md":"b23d01a7","my404.md":"c6efd2b1","plugins.md":"27f2b72e","pwa.md":"29dad110","quickstart.md":"a6e79e38","ssr.md":"e479afdd","themes.md":"d097e932","vue.md":"b8a02e4a","write-a-plugin.md":"7ef73afb"}
